jjfw/__init__.py
jjfw/extended_datetime.py
jjfw-0.0.1.dist-info/METADATA
jjfw-0.0.1.dist-info/WHEEL
jjfw-0.0.1.dist-info/top_level.txt
jjfw-0.0.1.dist-info/RECORD
